[ ["De2xsb7hNFY", {"title": "Natalia Nykiel - Pól kroku stad  (piosenka z filmu „Vaiana: skrab oceanu\")", "count": 2}], ["gK9Hyg2WJW4", {"title": "Create - Ptaki [Official Video]", "count": 1}], ["9gKZ2SlhVjg", {"title": "Karolina Artymowicz z \"Idol 5\" w gorzkich słowach o kulisach programu", "count": 1}], ["WbLcxGLeRVM", {"title": "Idol Polska - Odcinek 8 - Karolina Artymowicz", "count": 1}], ["5zq4ng9NcvA", {"title": "Idol Polska - Wielki Finał - Karolina Artymowicz - Little Talks (Of Monster and Man)", "count": 1}], ["qN4ooNx77u0", {"title": "Harry Styles - Sign of the Times", "count": 1}], ["F-S0M84Lo3o", {"title": "Daria Zawialow - Kundel Bury", "count": 1}], ["PbrSw6T3WPA", {"title": "Idol Polska - Wielki Finał - Karolina Artymowicz - Zanim pójdę (Happysad)", "count": 1}], ["GzU8KqOY8YA", {"title": "Sean Paul - No Lie ft. Dua Lipa", "count": 1}], ["bvEfYU4dk5k", {"title": "Jula w serialu \"M jak miłość\"!", "count": 1}], ["OoKHOhB1DEc", {"title": "Verba - Frajer ( 2017 )", "count": 1}], ["NTG8X_CbQMg", {"title": "SASZAN - DIZZY", "count": 1}], ["NGLxoKOvzu4", {"title": "Jason Derulo - Swalla (feat. Nicki Minaj & Ty Dolla $ign) (Official Music Video)", "count": 1}], ["1nPAJ0_pow8", {"title": "KAMIL BEDNAREK Feat MATHEO - TALIZMAN", "count": 1}], ["aatr_2MstrI", {"title": "Clean Bandit - Symphony feat. Zara Larsson [Official Video]", "count": 1}], ["0LfdlC5o1io", {"title": "DAWID KWIATKOWSKI - I'M WITH THE GIRL feat. TAELOR YUNG (prod. Konrad OldMoney)", "count": 1}], ["UQhVCnnxdHQ", {"title": "Beata Kozidrak -  Letni wiatr", "count": 1}], ["NLVm0U5fII8", {"title": "Beata - Niebiesko - Zielone", "count": 1}], ["C7lf3W_aCWM", {"title": "Beata Kozidrak szczerze o swoim rozwodzie i byłym mężu: \"Trzeba iść do przodu!\" (UWAGA! TVN)", "count": 1}], ["uE1uubeaNfo", {"title": "Michal Szpak - Tic Tac Clock", "count": 1}], ["xMurDYmMbAg", {"title": "Beata Kozidrak -- Płynę (HD)", "count": 1}], ["x4PfwFxl7LU", {"title": "Beata Kozidrak - \"Upiłam się Tobą\" live HD - Kocham Cię Polsko", "count": 1}], ["YWDPjYXOvco", {"title": "Mateusz Ziółko - Szkło [Official Music Video]", "count": 1}], ["CAYsgt91yQQ", {"title": "Mateusz Ziółko - Na nowo [Official Audio]", "count": 1}], ["VxTqSETB1TM", {"title": "Liber feat. Mateusz Ziółko - 7 Rzeczy (Oficjalny Teledysk)", "count": 1}], ["0sSLON6MKXM", {"title": "Na Dnie ( Choćbym spadał ) - Olga Szomańska & Mateusz Ziółko", "count": 1}], ["YLMJW62HE8A", {"title": "Andrzej Piaseczny - My (o mnie, o tobie, o nas) Lyric Video", "count": 1}], ["3ssoWhPH2eI", {"title": "Grzegorz Hyzy - O Pani!", "count": 1}], ["-I4yPkkJDV8", {"title": "Mateusz Ziółko - I Co? [Official Audio]", "count": 1}], ["B2S6qMA8ONY", {"title": "Sarsa - Dziele (Acoustic Version)", "count": 1}], ["zJk-nH_Kjos", {"title": "The Voice of Poland V - Sarsa Markiewicz - \"We Are the People\" - Przesłuchania w ciemno", "count": 1}], ["NXWrWvEnB6I", {"title": "Julia Wieniawa - Oddycham (Official Video)", "count": 1}], ["7csy4JnpLBg", {"title": "The Voice of Poland - Natalia Nykiel - „Trouble\"", "count": 1}], ["NOJzOZsxOhQ", {"title": "Puls regionu - Martyna Rempała - 29.05.17 r.", "count": 1}], ["eZYOfCsxUOs", {"title": "Martyna Rempała - Dla Nas Jesteś (Official Video)", "count": 1}], ["4fYl20285G0", {"title": "MARTYNA REMPAŁA -KRYSTIAN NA ZAWSZE POZOSTANIESZ Z NAMI (Alan Walker Cover)", "count": 1}], ["zpNvFhOra9E", {"title": "Martyna Rempała -Diamonds(Official Music Video Rihanna Cover)", "count": 1}], ["h6DteEY6B5U", {"title": "Adam Konkol & Paulina Urtnowska - Za tysiąc lat [Official Music Video]", "count": 1}], ["XPOX1sBlG4w", {"title": "Wika - Nie potrafię zapomnieć (Official Video)", "count": 1}], ["XoygY7zRH1A", {"title": "Ostatnia droga Krystiana - bez komentarza - imav.tv", "count": 1}], ["tjauapKzhas", {"title": "VERBA - KOCHAM CIĘ I CZEKAM ( NOWOŚĆ 2017 z płyty PRZERWANA LINIA ŻYCIA )", "count": 1}], ["j15GYcXaiE4", {"title": "Martyna Rempała-One Moment In Time (Whitney Houston Cover )", "count": 1}], ["sSmkaKA-6d0", {"title": "Patrycja Markowska & Grzegorz Markowski  Kołysanka", "count": 1}], ["dyB948SuX-Q", {"title": "T.LOVE - Blada [Official Music VIdeo]", "count": 1}], ["VtHKSfeQt_g", {"title": "Patrycja Markowska i Grzegorz Skawiński - Nie potrzeba mi nic więcej [Official Lyric Video]", "count": 1}], ["MVnL9lVskSc", {"title": "Mrozu - Szerokie wody [Live Session]", "count": 1}]]