[
   ["zulTf82fkt4", {"title": "Tina - Si Sám - Official video (prod. Tomi Popovič)", "count": 12}],
  ["JOYlFWwsVes", {"title": "Holki- Megamix", "count": 11}],
  ["2lx4vLeqL3U", {"title": "Kryštof - Ty a já", "count": 10}],
  ["baurmYHPhqQ", {"title": "Unique - Mi van a nevedben?", "count": 10}],
   ["34IzVKnk2yw", {"title": "Unique - Mozaik", "count": 10}],
  ["qy0sZLFYZ0E", {"title": "Holki- nejšťastnější pár", "count": 10}],
  ["qd-pxjzPQvw", {"title": "Sedmnáct", "count": 10}],
  ["de_x9JoUwCI", {"title": "Pavel Callta - Zrzka (Official Video)", "count": 9}],
   ["_spfCq_FAFE", {"title": "Kryštof - Cesta ft. Tomáš Klus", "count": 8}],
  ["de_x9JoUwCI", {"title": "Pavel Callta - Zrzka (Official Video)", "count": 9}],
  ["YR1OF4HEIyk", {"title": "Kristína & Robo Grigorov - Na vysokej skale", "count": 7}],
  ["YbCj3zkCywo", {"title": "Ewa Farna - Vino je grunt ft. Frantisek Segrado", "count": 10}],
  ["QoJ0Ku710ZY", {"title": "Verona-Nahodou", "count": 8}],
  ["erI5FZ2goh8", {"title": "Unique: Lassan Elhiszem", "count": 7}],
   ["ekFC8IeFK60", {"title": "CHINASKI - Slovenský klín (oficiální klip)", "count": 7}]

]